setup.py
ExcelControler/ExcelControler.py
ExcelControler/__init__.py
ExcelControler.egg-info/PKG-INFO
ExcelControler.egg-info/SOURCES.txt
ExcelControler.egg-info/dependency_links.txt
ExcelControler.egg-info/requires.txt
ExcelControler.egg-info/top_level.txt