Metadata-Version: 1.0
Name: ExcelControler
Version: 0.0.1
Summary: A light weight excel to list, or list to excel package
Home-page: http://holypanda.me
Author: holypanda
Author-email: panda93222@gmail.com
License: Holypanda Licence
Keywords: pip,datacanvas,excel,holypanda
Platform: any
